owlab/__init__.py
owlab/core/__init__.py
owlab/core/config.py
owlab/core/experiment.py
owlab/core/logger.py
owlab/lark/__init__.py
owlab/lark/api_bot.py
owlab/lark/sheet_manager.py
owlab/lark/webhook_bot.py
owlab/storage/__init__.py
owlab/storage/local_storage.py
owlab/swanlab/__init__.py
owlab/swanlab/adapter.py
owlab/swanlab/tensorboard_sync.py
owlab/swanlab/tracker.py
owlab/utils/__init__.py
owlab/utils/formatter.py
owlab/utils/retry.py
owlab/utils/schema_validator.py
owlab-0.1.2.dist-info/METADATA
owlab-0.1.2.dist-info/WHEEL
owlab-0.1.2.dist-info/licenses/LICENSE
owlab-0.1.2.dist-info/RECORD
