Metadata-Version: 2.4
Name: owlab
Version: 0.1.2
Summary: A Python toolkit for ML experiment management based on SwanLab and Lark
Project-URL: Homepage, https://github.com/Lounwb/OwLab
Project-URL: Documentation, https://github.com/Lounwb/OwLab#readme
Project-URL: Repository, https://github.com/Lounwb/OwLab
Project-URL: Issues, https://github.com/Lounwb/OwLab/issues
Project-URL: PyPI, https://pypi.org/project/owlab/
Author: OwLab Contributors
License: MIT
License-File: LICENSE
Keywords: experiment-tracking,feishu,lark,machine-learning,swanlab
Classifier: Development Status :: 3 - Alpha
Classifier: Intended Audience :: Developers
Classifier: Intended Audience :: Science/Research
Classifier: License :: OSI Approved :: MIT License
Classifier: Programming Language :: Python :: 3
Classifier: Programming Language :: Python :: 3.9
Classifier: Programming Language :: Python :: 3.10
Classifier: Programming Language :: Python :: 3.11
Classifier: Programming Language :: Python :: 3.12
Classifier: Topic :: Scientific/Engineering :: Artificial Intelligence
Classifier: Topic :: Software Development :: Libraries :: Python Modules
Requires-Python: >=3.9
Requires-Dist: loguru>=0.7.0
Requires-Dist: pydantic>=2.0.0
Requires-Dist: pyyaml>=6.0
Requires-Dist: requests>=2.31.0
Requires-Dist: swanlab>=0.3.0
Provides-Extra: dev
Requires-Dist: black>=23.0.0; extra == 'dev'
Requires-Dist: flake8>=6.0.0; extra == 'dev'
Requires-Dist: isort>=5.12.0; extra == 'dev'
Requires-Dist: mypy>=1.5.0; extra == 'dev'
Requires-Dist: pytest-cov>=4.1.0; extra == 'dev'
Requires-Dist: pytest-mock>=3.11.0; extra == 'dev'
Requires-Dist: pytest>=7.4.0; extra == 'dev'
Requires-Dist: twine>=5.0.0; extra == 'dev'
Requires-Dist: types-pyyaml>=6.0.0; extra == 'dev'
Requires-Dist: types-requests>=2.31.0; extra == 'dev'
